use_case_registry/__about__.py
use_case_registry/__init__.py
use_case_registry/enums.py
use_case_registry/errors.py
use_case_registry/py.typed
use_case_registry/registry.py
use_case_registry/base/__init__.py
use_case_registry/base/command.py
use_case_registry/base/repository.py
use_case_registry/base/schema_validator.py
use_case_registry/internals/__init__.py
use_case_registry/internals/errors.py
use_case_registry/pasers/__init__.py
use_case_registry/pasers/macros.py
use_case_registry/pasers/raw.py
use_case_registry-1.5.0.dist-info/METADATA
use_case_registry-1.5.0.dist-info/WHEEL
use_case_registry-1.5.0.dist-info/licenses/LICENSE.txt
use_case_registry-1.5.0.dist-info/RECORD
