Metadata-Version: 2.1
Name: use_case_registry
Version: 1.5.0
Summary: Registry class for Use Case implementation. They are basically meaningfull lists with some constraints.
Project-URL: Homepage, https://github.com/Tomperez98/use-case-registry
Project-URL: Documentation, https://tomperez98.github.io/use-case-registry/
Project-URL: Issues, https://github.com/Tomperez98/use-case-registry/issues
Project-URL: Source, https://github.com/Tomperez98/use-case-registry
Author-email: Tomas Perez Alvarez <tomasperezalvarez@gmail.com>
License-Expression: MIT
License-File: LICENSE.txt
Classifier: Development Status :: 4 - Beta
Classifier: Programming Language :: Python
Classifier: Programming Language :: Python :: 3.9
Classifier: Programming Language :: Python :: 3.10
Classifier: Programming Language :: Python :: 3.11
Classifier: Programming Language :: Python :: Implementation :: CPython
Classifier: Programming Language :: Python :: Implementation :: PyPy
Requires-Python: >=3.9
Requires-Dist: jinja2
Requires-Dist: mashumaro[orjson,yaml]
Requires-Dist: pydantic
Requires-Dist: result
Provides-Extra: dev
Requires-Dist: black; extra == 'dev'
Requires-Dist: hatch; extra == 'dev'
Requires-Dist: mkdocs-material; extra == 'dev'
Requires-Dist: mypy; extra == 'dev'
Requires-Dist: pip-tools; extra == 'dev'
Requires-Dist: pytest; extra == 'dev'
Requires-Dist: pytest-cov; extra == 'dev'
Requires-Dist: pytest-env; extra == 'dev'
Requires-Dist: ruff; extra == 'dev'
Requires-Dist: toml; extra == 'dev'
Requires-Dist: types-jsonschema; extra == 'dev'
Requires-Dist: types-pyyaml; extra == 'dev'
Provides-Extra: sqlalchemy
Requires-Dist: sqlalchemy; extra == 'sqlalchemy'
